bf_func/__init__.py
bf_func/retrying/__init__.py
bf_func/retrying/retrying.py
demos/__init__.py
bf_func-0.0.2.dist-info/LICENSE
bf_func-0.0.2.dist-info/METADATA
bf_func-0.0.2.dist-info/WHEEL
bf_func-0.0.2.dist-info/top_level.txt
bf_func-0.0.2.dist-info/RECORD
