Metadata-Version: 2.1
Name: bf-func
Version: 0.0.2
Summary: 公共方法库
Author: clark
Author-email: clark1203@foxmail.com
Classifier: Programming Language :: Python :: 3
Classifier: License :: OSI Approved :: MIT License
Classifier: Operating System :: OS Independent
Requires-Python: >=3
License-File: LICENSE
